taskswitch/__init__.py
taskswitch/__main__.py
taskswitch/commands.py
taskswitch/config.py
taskswitch/config_manager.py
taskswitch/db_state_manager.py
taskswitch/display.py
taskswitch/logging_config.py
taskswitch/migrate.py
taskswitch/models.py
taskswitch/reporting.py
taskswitch/shell.py
taskswitch/state_manager.py
taskswitch/timer.py
taskswitch/types.py
taskswitch/utils.py
taskswitch-4.0.0.dist-info/licenses/LICENSE
taskswitch-4.0.0.dist-info/METADATA
taskswitch-4.0.0.dist-info/WHEEL
taskswitch-4.0.0.dist-info/entry_points.txt
taskswitch-4.0.0.dist-info/top_level.txt
taskswitch-4.0.0.dist-info/RECORD
