Metadata-Version: 2.4
Name: taskswitch
Version: 4.0.0
Summary: Zero friction pure progress - A powerful CLI time tracker with SQLite backend
Author-email: DP26112 <davorin.p@pm.me>
License-Expression: MIT
Project-URL: Homepage, https://github.com/DP26112/simple-time-tracker
Project-URL: Repository, https://github.com/DP26112/simple-time-tracker
Project-URL: Issues, https://github.com/DP26112/simple-time-tracker/issues
Project-URL: Changelog, https://github.com/DP26112/simple-time-tracker/blob/main/CHANGELOG.md
Keywords: time-tracker,task-management,productivity,cli,sqlite,time-tracking,project-management
Classifier: Development Status :: 4 - Beta
Classifier: Intended Audience :: Developers
Classifier: Intended Audience :: End Users/Desktop
Classifier: Operating System :: OS Independent
Classifier: Programming Language :: Python :: 3
Classifier: Programming Language :: Python :: 3.8
Classifier: Programming Language :: Python :: 3.9
Classifier: Programming Language :: Python :: 3.10
Classifier: Programming Language :: Python :: 3.11
Classifier: Programming Language :: Python :: 3.12
Classifier: Topic :: Office/Business
Classifier: Topic :: Utilities
Classifier: Environment :: Console
Requires-Python: >=3.8
License-File: LICENSE
Requires-Dist: pytz>=2023.3
Requires-Dist: colorama>=0.4.6
Requires-Dist: peewee>=3.17.0
Requires-Dist: pyyaml>=6.0
Provides-Extra: dev
Requires-Dist: pytest>=7.4.0; extra == "dev"
Requires-Dist: pytest-cov>=4.1.0; extra == "dev"
Requires-Dist: black>=23.7.0; extra == "dev"
Requires-Dist: mypy>=1.5.0; extra == "dev"
Dynamic: license-file
